rawimage/__init__.py
rawimage/rawimage.py
rawimage/tests/__init__.py
rawimage/tests/test_rawimage.py
rawimage-0.0.2.dist-info/LICENSE.txt
rawimage-0.0.2.dist-info/METADATA
rawimage-0.0.2.dist-info/WHEEL
rawimage-0.0.2.dist-info/top_level.txt
rawimage-0.0.2.dist-info/RECORD
